{
  "contacts": [
    {
      "name": "Persephone",
      "phone": "+34 666 777 666",
      "id": "54a7"
    },
    {
      "name": "Hades",
      "phone": "You better don't call me",
      "id": "5368"
    },
    {
      "name": "Zeus",
      "phone": "+34 777 666 777",
      "id": "e0ec"
    },
    {
      "name": "Europa",
      "phone": "+34 767 676 767",
      "id": "10c0"
    },
    {
      "name": "Scott Summers",
      "phone": "+1 (212) 555 65 45",
      "id": "d617"
    },
    {
      "name": "Alex Summers",
      "phone": "+1 (212) 555 22 15",
      "id": "0439"
    }
  ]
}